ops_util/__init__.py
ops_util/core.py
ops_util-0.1.1.dist-info/METADATA
ops_util-0.1.1.dist-info/WHEEL
ops_util-0.1.1.dist-info/top_level.txt
ops_util-0.1.1.dist-info/RECORD
